investing_tickets_scrapper/__init__.py
investing_tickets_scrapper/investing_tickets_scrapper.py
investing_tickets_scrapper/main.py
investing_tickets_scrapper/scrapper.py
src/__init__.py
src/scrapper.py
investing_tickets_scrapper-0.0.3.dist-info/LICENSE.txt
investing_tickets_scrapper-0.0.3.dist-info/METADATA
investing_tickets_scrapper-0.0.3.dist-info/WHEEL
investing_tickets_scrapper-0.0.3.dist-info/top_level.txt
investing_tickets_scrapper-0.0.3.dist-info/RECORD
