Metadata-Version: 2.1
Name: investing-tickets-scrapper
Version: 0.0.3
Summary: Scraps stock tickets from "Investing.com" using Selenium and parse using BeautifulSoup
Home-page: UNKNOWN
Author: Lucas Rocha
Author-email: lucasrocha.png@gmail.com
License: UNKNOWN
Keywords: python,tickers,index,stocks,exchange,investing
Platform: UNKNOWN
Classifier: Development Status :: 5 - Production/Stable
Classifier: Intended Audience :: Developers
Classifier: Programming Language :: Python :: 3
Classifier: License :: OSI Approved :: Apache Software License
Classifier: Operating System :: Unix
Classifier: Operating System :: MacOS :: MacOS X
Classifier: Operating System :: Microsoft :: Windows
License-File: LICENSE.txt
Requires-Dist: pandas (>=1.3.3)
Requires-Dist: selenium (>=4.1.3)
Requires-Dist: beautifulsoup4 (>=4.4.1)
